flexipatch/__init__.py
flexipatch/patcher.py
flexipatch-0.1.0.dist-info/licenses/LICENSE
flexipatch-0.1.0.dist-info/METADATA
flexipatch-0.1.0.dist-info/WHEEL
flexipatch-0.1.0.dist-info/top_level.txt
flexipatch-0.1.0.dist-info/RECORD
