Metadata-Version: 2.4
Name: flexipatch
Version: 0.1.0
Summary: The forgiving patch tool for AI-powered coding.
Author-email: ParisNeo <parisneoai@gmail.com>
License:                                  Apache License
Project-URL: Homepage, https://github.com/ParisNeo/flexipatch
Project-URL: Bug Tracker, https://github.com/ParisNeo/flexipatch/issues
Keywords: patch,diff,llm,ai,refactor,robust
Classifier: Programming Language :: Python :: 3
Classifier: Programming Language :: Python :: 3.7
Classifier: Programming Language :: Python :: 3.8
Classifier: Programming Language :: Python :: 3.9
Classifier: Programming Language :: Python :: 3.10
Classifier: Programming Language :: Python :: 3.11
Classifier: License :: OSI Approved :: Apache Software License
Classifier: Operating System :: OS Independent
Classifier: Intended Audience :: Developers
Classifier: Topic :: Software Development :: Libraries :: Python Modules
Classifier: Topic :: Utilities
Requires-Python: >=3.7
License-File: LICENSE
Dynamic: license-file
